mysqldb_mcp_server/__init__.py
mysqldb_mcp_server/server.py
mseep_mysqldb_mcp_server-0.1.6.dist-info/METADATA
mseep_mysqldb_mcp_server-0.1.6.dist-info/WHEEL
mseep_mysqldb_mcp_server-0.1.6.dist-info/entry_points.txt
mseep_mysqldb_mcp_server-0.1.6.dist-info/licenses/LICENSE
mseep_mysqldb_mcp_server-0.1.6.dist-info/RECORD
